{
	"apps": [
		{
			"name": "nodetick",
			"script": "/home/cnnitouch/node/nodetick/dist/index.js",
			"output": "/dev/null",
			"node_args": "--inspect --max_old_space_size=500"
		},
		{
			"name": "multi_sync",
			"script": "/home/cnnitouch/node/multi_sync/index.js",
			"output": "/dev/null"
		},
		{
			"name": "util_server",
			"cwd": "/home/cnnitouch/node/util_server_main/dist/",
			"script": "index.js",
			"env": { "NODE_ENV": "production" },
			"output": "/dev/null"
		},
		{
			"name": "graphql",
			"cwd": "/home/cnnitouch/node/cnnitouch-graphql-server/dist/",
			"script": "index.js",
			"output": "/dev/null"
		},
		{
			"name": "caspar",
			"cwd": "/home/cnnitouch/node/cnnitouch-casparcg-control-server/dist/",
			"script": "index.js",
			"output": "/dev/null"
		}
	]
}
